MPC2860-0.3.data/platlib/_motion_2860.pyd
MPC2860-0.3.data/platlib/MPC2860/MPC2860.dll
MPC2860-0.3.data/platlib/MPC2860/MPC2860.lib
MPC2860-0.3.data/platlib/MPC2860/MPC2860CFG.txt
MPC2860-0.3.data/platlib/MPC2860/__init__.py
MPC2860-0.3.data/platlib/MPC2860/_motion_2860.pyd
MPC2860-0.3.data/platlib/MPC2860/motion_2860.i
MPC2860-0.3.data/platlib/MPC2860/motion_2860.py
MPC2860-0.3.dist-info/LICENSE
MPC2860-0.3.dist-info/METADATA
MPC2860-0.3.dist-info/WHEEL
MPC2860-0.3.dist-info/top_level.txt
MPC2860-0.3.dist-info/RECORD
